airflow/providers/sqlite/__init__.py
airflow/providers/sqlite/get_provider_info.py
airflow/providers/sqlite/hooks/__init__.py
airflow/providers/sqlite/hooks/sqlite.py
airflow/providers/sqlite/operators/__init__.py
airflow/providers/sqlite/operators/sqlite.py
apache_airflow_providers_sqlite-3.5.0.dist-info/LICENSE
apache_airflow_providers_sqlite-3.5.0.dist-info/METADATA
apache_airflow_providers_sqlite-3.5.0.dist-info/NOTICE
apache_airflow_providers_sqlite-3.5.0.dist-info/WHEEL
apache_airflow_providers_sqlite-3.5.0.dist-info/entry_points.txt
apache_airflow_providers_sqlite-3.5.0.dist-info/top_level.txt
apache_airflow_providers_sqlite-3.5.0.dist-info/RECORD
